{"numFailedTestSuites":1,"numFailedTests":1,"numPassedTestSuites":0,"numPassedTests":2,"numPendingTestSuites":0,"numPendingTests":0,"numRuntimeErrorTestSuites":0,"numTodoTests":0,"numTotalTestSuites":1,"numTotalTests":3,"openHandles":[],"snapshot":{"added":0,"didUpdate":false,"failure":false,"filesAdded":0,"filesRemoved":0,"filesRemovedList":[],"filesUnmatched":0,"filesUpdated":0,"matched":0,"total":0,"unchecked":0,"uncheckedKeysByFile":[],"unmatched":0,"updated":0},"startTime":1652633007312,"success":false,"testResults":[{"assertionResults":[{"ancestorTitles":["Trade"],"failureMessages":[],"fullName":"Trade should create an instance","location":null,"status":"passed","title":"should create an instance"},{"ancestorTitles":["Trade"],"failureMessages":[],"fullName":"Trade first test case","location":null,"status":"passed","title":"first test case"},{"ancestorTitles":["Trade"],"failureMessages":["Error: \u001b[2mexpect(\u001b[22m\u001b[31mreceived\u001b[39m\u001b[2m).\u001b[22mtoBe\u001b[2m(\u001b[22m\u001b[32mexpected\u001b[39m\u001b[2m) // Object.is equality\u001b[22m\n\nExpected: \u001b[32m16\u001b[39m\nReceived: \u001b[31m24\u001b[39m\n    at C:\\Users\\kn71026MSI\\Desktop\\w12-hw\\w12-hw\\apps\\potter\\src\\app\\trade.spec.ts:18:25\n    at _ZoneDelegate.Object.<anonymous>._ZoneDelegate.invoke (C:\\Users\\kn71026MSI\\Desktop\\w12-hw\\w12-hw\\node_modules\\zone.js\\bundles\\zone-testing-bundle.umd.js:409:30)\n    at ProxyZoneSpec.Object.<anonymous>.ProxyZoneSpec.onInvoke (C:\\Users\\kn71026MSI\\Desktop\\w12-hw\\w12-hw\\node_modules\\zone.js\\bundles\\zone-testing-bundle.umd.js:3803:43)\n    at _ZoneDelegate.Object.<anonymous>._ZoneDelegate.invoke (C:\\Users\\kn71026MSI\\Desktop\\w12-hw\\w12-hw\\node_modules\\zone.js\\bundles\\zone-testing-bundle.umd.js:408:56)\n    at Zone.Object.<anonymous>.Zone.run (C:\\Users\\kn71026MSI\\Desktop\\w12-hw\\w12-hw\\node_modules\\zone.js\\bundles\\zone-testing-bundle.umd.js:169:47)\n    at Object.wrappedFunc (C:\\Users\\kn71026MSI\\Desktop\\w12-hw\\w12-hw\\node_modules\\zone.js\\bundles\\zone-testing-bundle.umd.js:4288:34)\n    at Promise.then.completed (C:\\Users\\kn71026MSI\\Desktop\\w12-hw\\w12-hw\\node_modules\\jest-circus\\build\\utils.js:391:28)\n    at new Promise (<anonymous>)\n    at callAsyncCircusFn (C:\\Users\\kn71026MSI\\Desktop\\w12-hw\\w12-hw\\node_modules\\jest-circus\\build\\utils.js:316:10)\n    at _callCircusTest (C:\\Users\\kn71026MSI\\Desktop\\w12-hw\\w12-hw\\node_modules\\jest-circus\\build\\run.js:218:40)\n    at processTicksAndRejections (internal/process/task_queues.js:95:5)\n    at _runTest (C:\\Users\\kn71026MSI\\Desktop\\w12-hw\\w12-hw\\node_modules\\jest-circus\\build\\run.js:155:3)\n    at _runTestsForDescribeBlock (C:\\Users\\kn71026MSI\\Desktop\\w12-hw\\w12-hw\\node_modules\\jest-circus\\build\\run.js:66:9)\n    at _runTestsForDescribeBlock (C:\\Users\\kn71026MSI\\Desktop\\w12-hw\\w12-hw\\node_modules\\jest-circus\\build\\run.js:60:9)\n    at run (C:\\Users\\kn71026MSI\\Desktop\\w12-hw\\w12-hw\\node_modules\\jest-circus\\build\\run.js:25:3)\n    at runAndTransformResultsToJestFormat (C:\\Users\\kn71026MSI\\Desktop\\w12-hw\\w12-hw\\node_modules\\jest-circus\\build\\legacy-code-todo-rewrite\\jestAdapterInit.js:170:21)"],"fullName":"Trade second test case","location":null,"status":"failed","title":"second test case"}],"endTime":1652633009885,"message":"\u001b[1m\u001b[31m  \u001b[1m● \u001b[22m\u001b[1mTrade › second test case\u001b[39m\u001b[22m\n\n    \u001b[2mexpect(\u001b[22m\u001b[31mreceived\u001b[39m\u001b[2m).\u001b[22mtoBe\u001b[2m(\u001b[22m\u001b[32mexpected\u001b[39m\u001b[2m) // Object.is equality\u001b[22m\n\n    Expected: \u001b[32m16\u001b[39m\n    Received: \u001b[31m24\u001b[39m\n\u001b[2m\u001b[22m\n\u001b[2m    \u001b[0m \u001b[90m 16 |\u001b[39m   test(\u001b[32m'second test case'\u001b[39m\u001b[33m,\u001b[39m () \u001b[33m=>\u001b[39m {\u001b[0m\u001b[22m\n\u001b[2m    \u001b[0m \u001b[90m 17 |\u001b[39m     trade\u001b[33m.\u001b[39mcheckout([\u001b[35m1\u001b[39m\u001b[33m,\u001b[39m \u001b[35m2\u001b[39m])\u001b[33m;\u001b[39m\u001b[0m\u001b[22m\n\u001b[2m    \u001b[0m\u001b[31m\u001b[1m>\u001b[22m\u001b[2m\u001b[39m\u001b[90m 18 |\u001b[39m     expect(trade\u001b[33m.\u001b[39mprice)\u001b[33m.\u001b[39mtoBe(\u001b[35m16\u001b[39m)\u001b[33m;\u001b[39m\u001b[0m\u001b[22m\n\u001b[2m    \u001b[0m \u001b[90m    |\u001b[39m                         \u001b[31m\u001b[1m^\u001b[22m\u001b[2m\u001b[39m\u001b[0m\u001b[22m\n\u001b[2m    \u001b[0m \u001b[90m 19 |\u001b[39m   })\u001b[33m;\u001b[39m\u001b[0m\u001b[22m\n\u001b[2m    \u001b[0m \u001b[90m 20 |\u001b[39m })\u001b[33m;\u001b[39m\u001b[0m\u001b[22m\n\u001b[2m    \u001b[0m \u001b[90m 21 |\u001b[39m\u001b[0m\u001b[22m\n\u001b[2m\u001b[22m\n\u001b[2m      \u001b[2mat \u001b[22m\u001b[2m\u001b[0m\u001b[36msrc/app/trade.spec.ts\u001b[39m\u001b[0m\u001b[2m:18:25\u001b[22m\u001b[2m\u001b[22m\n\u001b[2m      \u001b[2mat _ZoneDelegate.Object.<anonymous>._ZoneDelegate.invoke (\u001b[22m\u001b[2m../../node_modules/zone.js/bundles/zone-testing-bundle.umd.js\u001b[2m:409:30)\u001b[22m\u001b[2m\u001b[22m\n\u001b[2m      \u001b[2mat ProxyZoneSpec.Object.<anonymous>.ProxyZoneSpec.onInvoke (\u001b[22m\u001b[2m../../node_modules/zone.js/bundles/zone-testing-bundle.umd.js\u001b[2m:3803:43)\u001b[22m\u001b[2m\u001b[22m\n\u001b[2m      \u001b[2mat _ZoneDelegate.Object.<anonymous>._ZoneDelegate.invoke (\u001b[22m\u001b[2m../../node_modules/zone.js/bundles/zone-testing-bundle.umd.js\u001b[2m:408:56)\u001b[22m\u001b[2m\u001b[22m\n\u001b[2m      \u001b[2mat Zone.Object.<anonymous>.Zone.run (\u001b[22m\u001b[2m../../node_modules/zone.js/bundles/zone-testing-bundle.umd.js\u001b[2m:169:47)\u001b[22m\u001b[2m\u001b[22m\n\u001b[2m      \u001b[2mat Object.wrappedFunc (\u001b[22m\u001b[2m../../node_modules/zone.js/bundles/zone-testing-bundle.umd.js\u001b[2m:4288:34)\u001b[22m\u001b[2m\u001b[22m\n","name":"C:\\Users\\kn71026MSI\\Desktop\\w12-hw\\w12-hw\\apps\\potter\\src\\app\\trade.spec.ts","startTime":1652633008222,"status":"failed","summary":""}],"wasInterrupted":false,"coverageMap":{"C:\\Users\\kn71026MSI\\Desktop\\w12-hw\\w12-hw\\apps\\potter\\src\\app\\trade.ts":{"path":"C:\\Users\\kn71026MSI\\Desktop\\w12-hw\\w12-hw\\apps\\potter\\src\\app\\trade.ts","statementMap":{"0":{"start":{"line":2,"column":10},"end":{"line":2,"column":21}},"1":{"start":{"line":3,"column":10},"end":{"line":3,"column":26}},"2":{"start":{"line":6,"column":4},"end":{"line":6,"column":52}},"3":{"start":{"line":10,"column":4},"end":{"line":10,"column":28}},"4":{"start":{"line":1,"column":0},"end":{"line":1,"column":13}}},"fnMap":{"0":{"name":"(anonymous_0)","decl":{"start":{"line":1,"column":0},"end":{"line":1,"column":13}},"loc":{"start":{"line":1,"column":0},"end":{"line":12,"column":1}}},"1":{"name":"(anonymous_1)","decl":{"start":{"line":5,"column":2},"end":{"line":5,"column":10}},"loc":{"start":{"line":5,"column":27},"end":{"line":7,"column":3}}},"2":{"name":"(anonymous_2)","decl":{"start":{"line":9,"column":2},"end":{"line":9,"column":6}},"loc":{"start":{"line":9,"column":11},"end":{"line":11,"column":3}}}},"branchMap":{},"s":{"0":2,"1":2,"2":2,"3":2,"4":1},"f":{"0":2,"1":2,"2":2},"b":{}}}}